streamlit_autorefresh/__init__.py
streamlit_autorefresh/frontend/build/asset-manifest.json
streamlit_autorefresh/frontend/build/index.html
streamlit_autorefresh/frontend/build/precache-manifest.410d6a3f2e708cfa56b6d9e4ad8a186d.js
streamlit_autorefresh/frontend/build/precache-manifest.fb4637176de96fc72e9a091be53dbacf.js
streamlit_autorefresh/frontend/build/service-worker.js
streamlit_autorefresh/frontend/build/static/js/2.501b5008.chunk.js
streamlit_autorefresh/frontend/build/static/js/2.501b5008.chunk.js.LICENSE.txt
streamlit_autorefresh/frontend/build/static/js/2.501b5008.chunk.js.map
streamlit_autorefresh/frontend/build/static/js/2.b15cb7c9.chunk.js
streamlit_autorefresh/frontend/build/static/js/2.b15cb7c9.chunk.js.LICENSE.txt
streamlit_autorefresh/frontend/build/static/js/2.b15cb7c9.chunk.js.map
streamlit_autorefresh/frontend/build/static/js/main.d7c3a224.chunk.js
streamlit_autorefresh/frontend/build/static/js/main.d7c3a224.chunk.js.map
streamlit_autorefresh/frontend/build/static/js/main.ec9ffac2.chunk.js
streamlit_autorefresh/frontend/build/static/js/main.ec9ffac2.chunk.js.map
streamlit_autorefresh/frontend/build/static/js/runtime-main.44d30fc2.js
streamlit_autorefresh/frontend/build/static/js/runtime-main.44d30fc2.js.map
streamlit_autorefresh-1.0.1.dist-info/LICENSE
streamlit_autorefresh-1.0.1.dist-info/METADATA
streamlit_autorefresh-1.0.1.dist-info/WHEEL
streamlit_autorefresh-1.0.1.dist-info/top_level.txt
streamlit_autorefresh-1.0.1.dist-info/RECORD
