Metadata-Version: 2.1
Name: streamlit-autorefresh
Version: 1.0.1
Summary: Simple way to autorefresh your Streamlit apps
Home-page: https://github.com/kmcgrady/streamlit-autorefresh
Author: Ken McGrady
Author-email: ken.mcgrady@gmail.com
License: UNKNOWN
Platform: UNKNOWN
Requires-Python: >=3.6
License-File: LICENSE
